dnora_destine/__init__.py
dnora_destine/polytope_functions.py
dnora_destine/ice/__init__.py
dnora_destine/ice/ice_readers.py
dnora_destine/modelrun/__init__.py
dnora_destine/modelrun/templates.py
dnora_destine/spectra/__init__.py
dnora_destine/spectra/spectral_readers.py
dnora_destine/wind/__init__.py
dnora_destine/wind/wind_readers.py
dnora_destine-0.1.3.dist-info/licenses/LICENSE
dnora_destine-0.1.3.dist-info/METADATA
dnora_destine-0.1.3.dist-info/WHEEL
dnora_destine-0.1.3.dist-info/top_level.txt
dnora_destine-0.1.3.dist-info/RECORD
