Metadata-Version: 2.4
Name: dnora-destine
Version: 0.1.3
Summary: Add-on to dnora: Access to DestinE weather products
Author-email: Konstantinos Christakos <konstantinosc@met.no>, Jan-Victor Björkqvist <janvb@met.no>
License: MIT License
Project-URL: homepage, https://github.com/MET-OM/dnora-destine
Project-URL: download, https://github.com/MET-OM/dnora-destine
Requires-Python: <=3.13,>=3.9
License-File: LICENSE
Requires-Dist: dnora>=2.2.1
Requires-Dist: polytope-client
Requires-Dist: cfgrib
Requires-Dist: eccodes==2.41.0
Provides-Extra: test
Requires-Dist: pytest>=7.0; extra == "test"
Dynamic: license-file
